dgipy/__init__.py
dgipy/data_utils.py
dgipy/dgidb.py
dgipy/graph_app.py
dgipy/network_graph.py
dgipy/vcf.py
dgipy/integrations/__init__.py
dgipy/integrations/clinical_trials.py
dgipy/network/__init__.py
dgipy/network/construct.py
dgipy/network/export.py
dgipy/queries/__init__.py
dgipy/queries/get_all_drugs.graphql
dgipy/queries/get_all_genes.graphql
dgipy/queries/get_drug_applications.graphql
dgipy/queries/get_drugs.graphql
dgipy/queries/get_gene_categories.graphql
dgipy/queries/get_genes.graphql
dgipy/queries/get_interactions_by_drug.graphql
dgipy/queries/get_interactions_by_gene.graphql
dgipy/queries/get_sources.graphql
dgipy-0.1.0.dist-info/LICENSE
dgipy-0.1.0.dist-info/METADATA
dgipy-0.1.0.dist-info/WHEEL
dgipy-0.1.0.dist-info/top_level.txt
dgipy-0.1.0.dist-info/RECORD
