Metadata-Version: 2.1
Name: dgipy
Version: 0.1.0
Summary: Python wrapper for accessing an instance of DGIdb v5 database
Author-email: Matthew Cannon <Matthew.Cannon2@nationwidechildrens.org>, Rohit Basu <Rohit.Basu@nationwidechildrens.org>, James Stevenson <james.stevenson@nationwidechildrens.org>
License: MIT License
Project-URL: Homepage, https://github.com/genomicmedlab/dgipy
Project-URL: Documentation, https://github.com/genomicmedlab/dgipy
Project-URL: Changelog, https://github.com/genomicmedlab/dgipy/releases
Project-URL: Source, https://github.com/genomicmedlab/dgipy
Project-URL: Bug Tracker, https://github.com/genomicmedlab/dgipy/issues
Classifier: Development Status :: 3 - Alpha
Classifier: Intended Audience :: Science/Research
Classifier: Intended Audience :: Developers
Classifier: Topic :: Scientific/Engineering :: Bio-Informatics
Classifier: License :: OSI Approved :: MIT License
Classifier: Programming Language :: Python :: 3
Classifier: Programming Language :: Python :: 3.11
Classifier: Programming Language :: Python :: 3.12
Classifier: Programming Language :: Python :: 3.13
Requires-Python: >=3.11
License-File: LICENSE
Requires-Dist: regbot~=0.1.2
Requires-Dist: requests
Requires-Dist: gql[requests]
Requires-Dist: pandas~=2.0
Requires-Dist: dash
Requires-Dist: dash-bootstrap-components
Requires-Dist: plotly
Requires-Dist: networkx[default]
Requires-Dist: dash_cytoscape
Provides-Extra: tests
Requires-Dist: pytest; extra == "tests"
Requires-Dist: pytest-cov; extra == "tests"
Requires-Dist: pytest-benchmark; extra == "tests"
Requires-Dist: requests_mock; extra == "tests"
Provides-Extra: dev
Requires-Dist: pre-commit>=3.7.1; extra == "dev"
Requires-Dist: ruff==0.5.0; extra == "dev"
Provides-Extra: docs
Requires-Dist: sphinx==6.1.3; extra == "docs"
Requires-Dist: sphinx-autodoc-typehints==1.22.0; extra == "docs"
Requires-Dist: sphinx-autobuild==2021.3.14; extra == "docs"
Requires-Dist: sphinx-copybutton==0.5.2; extra == "docs"
Requires-Dist: sphinxext-opengraph==0.8.2; extra == "docs"
Requires-Dist: furo==2023.3.27; extra == "docs"
Requires-Dist: sphinx-github-changelog==1.2.1; extra == "docs"
